krocus/Blocks.py
krocus/Fasta.py
krocus/Fastas.py
krocus/Fastq.py
krocus/Gene.py
krocus/InputTypes.py
krocus/Kmers.py
krocus/Krocus.py
krocus/KrocusDatabaseDownloader.py
krocus/MlstProfile.py
krocus/PubmlstGetter.py
krocus/Read.py
krocus/__init__.py
krocus-1.0.3.data/scripts/krocus
krocus-1.0.3.data/scripts/krocus_database_downloader
krocus-1.0.3.dist-info/DESCRIPTION.rst
krocus-1.0.3.dist-info/METADATA
krocus-1.0.3.dist-info/RECORD
krocus-1.0.3.dist-info/WHEEL
krocus-1.0.3.dist-info/metadata.json
krocus-1.0.3.dist-info/top_level.txt
